README.md
setup.py
salt_container_map.egg-info/PKG-INFO
salt_container_map.egg-info/SOURCES.txt
salt_container_map.egg-info/dependency_links.txt
salt_container_map.egg-info/entry_points.txt
salt_container_map.egg-info/requires.txt
salt_container_map.egg-info/top_level.txt
saltcontainermap/__init__.py
saltcontainermap/modinstall.py
saltcontainermap/extmods/__init__.py
saltcontainermap/extmods/lazy_yaml.py
saltcontainermap/modules/__init__.py
saltcontainermap/modules/container_map.py
saltcontainermap/states/__init__.py
saltcontainermap/states/container_map.py