Metadata-Version: 1.1
Name: salt-container-map
Version: 0.2.2
Summary: Configuration management and implicit dependency setup for Docker containers in SaltStack.
Home-page: https://github.com/merll/salt-container-map
Author: Matthias Erll
Author-email: matthias@erll.de
License: MIT
Keywords: docker,deployment,salt
Platform: OS Independent
Classifier: Environment :: Web Environment
Classifier: Intended Audience :: Developers
Classifier: License :: OSI Approved :: MIT License
Classifier: Operating System :: OS Independent
Classifier: Programming Language :: Python
Classifier: Topic :: Software Development :: Libraries :: Python Modules
Classifier: Topic :: Software Development :: Build Tools
Classifier: Topic :: System :: Software Distribution
Classifier: Development Status :: 4 - Beta
Classifier: Programming Language :: Python :: 2.7
Classifier: Programming Language :: Python :: 3.4
